sleep_hotkey/__init__.py
sleep_hotkey/sleep_hotkey.py
sleep_hotkey-0.0.1.dist-info/LICENSE
sleep_hotkey-0.0.1.dist-info/METADATA
sleep_hotkey-0.0.1.dist-info/WHEEL
sleep_hotkey-0.0.1.dist-info/top_level.txt
sleep_hotkey-0.0.1.dist-info/RECORD
