Metadata-Version: 2.1
Name: sleep-hotkey
Version: 0.0.1
Summary: Sleep Hotkey
Home-page: https://github.com/HenleyKuang/sleep-hotkey
Author: Henley Kuang
Author-email: hekuang@ucdavis.edu
License: GPL
Keywords: python sleep hotkey smart controlled
Platform: UNKNOWN
Classifier: Development Status :: 5 - Production/Stable
Classifier: Intended Audience :: Developers
Classifier: License :: OSI Approved :: GNU General Public License v3 (GPLv3)
Classifier: Programming Language :: Python
Classifier: Programming Language :: Python :: 3
Classifier: Programming Language :: Python :: 3.6
Classifier: Programming Language :: Python :: 3.7
Classifier: Topic :: Utilities
Requires-Python: >=3.6
Requires-Dist: keyboard
